fastapi_rf-0.1.0a3.dist-info/METADATA
fastapi_rf-0.1.0a3.dist-info/WHEEL
fastapi_rf-0.1.0a3.dist-info/entry_points.txt
fastapi_rf-0.1.0a3.dist-info/licenses/LICENSE
frf/__init__.py
frf/endpoints/__init__.py
frf/endpoints/base_endpoint.py
frf/pagination/__init__.py
frf/routers/__init__.py
frf/routers/base_router.py
frf/schemas/__init__.py
frf/security/__init__.py
mock_project/__init__.py
mock_project/main.py
fastapi_rf-0.1.0a3.dist-info/RECORD
